README.rst
setup.py
gredis/__init__.py
gredis/client.py
gredis/connection.py
gredis.egg-info/PKG-INFO
gredis.egg-info/SOURCES.txt
gredis.egg-info/dependency_links.txt
gredis.egg-info/pbr.json
gredis.egg-info/requires.txt
gredis.egg-info/top_level.txt